[
  {
    "content": "Bug 1 - Investiguer 'Save failed' sur ajout de secret",
    "status": "completed"
  },
  {
    "content": "Bug 1 - Reproduire et fixer 'Save failed'",
    "status": "completed"
  },
  {
    "content": "Bug 2 - Investiguer rejet mnemonic valide a l'unlock",
    "status": "completed"
  },
  {
    "content": "Bug 2 - Reproduire et fixer rejet mnemonic",
    "status": "completed"
  },
  {
    "content": "Tests backend complets sur les 2 fixes",
    "status": "completed"
  },
  {
    "content": "Build frontend prod + restart services",
    "status": "completed"
  }
]