[
  {
    "content": "Tokenomics : gold_coin_front.png au centre du donut (couvrir le volume) + déplacer Total Supply 1B en dessous/légende",
    "status": "completed"
  },
  {
    "content": "ROISimulator : gold_coin_3d.png en background + overlay pour lisibilité texte",
    "status": "completed"
  },
  {
    "content": "Hero carousel : ajouter logo_v4_matrix_face.png (MATRIX PROPHET) aux variantes",
    "status": "completed"
  },
  {
    "content": "Vérifier lint + screenshot des 3 sections modifiées",
    "status": "completed"
  }
]